pulseqzero/__init__.py
pulseqzero/math.py
pulseqzero/adapter/__init__.py
pulseqzero/adapter/adc.py
pulseqzero/adapter/delay.py
pulseqzero/adapter/extended_trap_grad.py
pulseqzero/adapter/grads.py
pulseqzero/adapter/opts.py
pulseqzero/adapter/pulses.py
pulseqzero/adapter/seq_convert.py
pulseqzero/adapter/sequence.py
pulseqzero-0.2.1.dist-info/licenses/LICENSE
pulseqzero-0.2.1.dist-info/METADATA
pulseqzero-0.2.1.dist-info/WHEEL
pulseqzero-0.2.1.dist-info/top_level.txt
pulseqzero-0.2.1.dist-info/RECORD
