Metadata-Version: 2.4
Name: pulseqzero
Version: 0.2.1
Summary: Use PyPulseq for MRI sequence definitions in MR-zero
Author-email: Jonathan Endres <jonathan.endres@uk-erlangen.de>
Project-URL: Repository, https://github.com/pulseq-frame/pulseq-zero
Classifier: Programming Language :: Python :: 3
Classifier: Operating System :: OS Independent
Classifier: License :: OSI Approved :: GNU Affero General Public License v3 or later (AGPLv3+)
License-File: LICENSE
Dynamic: license-file
